{
    "key": "value",
    "boolean": true,
    "number": 123,
    "nullType": null,
    "simpleArray": ["item1", "item2", "item3"],
    "arrayInArray": [
        ["item1", "item2"],
        ["item3", "item4"]
    ],
    "object": {
        "nestedKey": "nestedValue",
        "nestedArray": ["item1", "item2", "item3"],
        "nestedObject": {
            "key": "value"
        }
    },
    "array": [
        {
            "key": "value"
        },
        {
            "key": "value"
        }
    ]
}